{
  "url": "https://api.github.com/repos/andreasgriffin/bitcoin-safe/releases/183216584",
  "assets_url": "https://api.github.com/repos/andreasgriffin/bitcoin-safe/releases/183216584/assets",
  "upload_url": "https://uploads.github.com/repos/andreasgriffin/bitcoin-safe/releases/183216584/assets{?name,label}",
  "html_url": "https://github.com/andreasgriffin/bitcoin-safe/releases/tag/1.0.0b2",
  "id": 183216584,
  "author": {
    "login": "andreasgriffin",
    "id": 116060138,
    "node_id": "U_kgDOBurv6g",
    "avatar_url": "https://avatars.githubusercontent.com/u/116060138?v=4",
    "gravatar_id": "",
    "url": "https://api.github.com/users/andreasgriffin",
    "html_url": "https://github.com/andreasgriffin",
    "followers_url": "https://api.github.com/users/andreasgriffin/followers",
    "following_url": "https://api.github.com/users/andreasgriffin/following{/other_user}",
    "gists_url": "https://api.github.com/users/andreasgriffin/gists{/gist_id}",
    "starred_url": "https://api.github.com/users/andreasgriffin/starred{/owner}{/repo}",
    "subscriptions_url": "https://api.github.com/users/andreasgriffin/subscriptions",
    "organizations_url": "https://api.github.com/users/andreasgriffin/orgs",
    "repos_url": "https://api.github.com/users/andreasgriffin/repos",
    "events_url": "https://api.github.com/users/andreasgriffin/events{/privacy}",
    "received_events_url": "https://api.github.com/users/andreasgriffin/received_events",
    "type": "User",
    "user_view_type": "public",
    "site_admin": false
  },
  "node_id": "RE_kwDOJfpJyM4K66nI",
  "tag_name": "1.0.0b2",
  "target_commitish": "main",
  "name": "1.0.0b2",
  "draft": false,
  "prerelease": false,
  "created_at": "2024-11-02T14:56:24Z",
  "published_at": "2024-11-02T15:56:54Z",
  "assets": [
    {
      "url": "https://api.github.com/repos/andreasgriffin/bitcoin-safe/releases/assets/203616090",
      "id": 203616090,
      "node_id": "RA_kwDOJfpJyM4MIu9a",
      "name": "Bitcoin-Safe-1.0.0b2.msi",
      "label": "",
      "uploader": {
        "login": "andreasgriffin",
        "id": 116060138,
        "node_id": "U_kgDOBurv6g",
        "avatar_url": "https://avatars.githubusercontent.com/u/116060138?v=4",
        "gravatar_id": "",
        "url": "https://api.github.com/users/andreasgriffin",
        "html_url": "https://github.com/andreasgriffin",
        "followers_url": "https://api.github.com/users/andreasgriffin/followers",
        "following_url": "https://api.github.com/users/andreasgriffin/following{/other_user}",
        "gists_url": "https://api.github.com/users/andreasgriffin/gists{/gist_id}",
        "starred_url": "https://api.github.com/users/andreasgriffin/starred{/owner}{/repo}",
        "subscriptions_url": "https://api.github.com/users/andreasgriffin/subscriptions",
        "organizations_url": "https://api.github.com/users/andreasgriffin/orgs",
        "repos_url": "https://api.github.com/users/andreasgriffin/repos",
        "events_url": "https://api.github.com/users/andreasgriffin/events{/privacy}",
        "received_events_url": "https://api.github.com/users/andreasgriffin/received_events",
        "type": "User",
        "user_view_type": "public",
        "site_admin": false
      },
      "content_type": "application/octet-stream",
      "state": "uploaded",
      "size": 190174219,
      "download_count": 1,
      "created_at": "2024-11-02T15:51:55Z",
      "updated_at": "2024-11-02T15:53:09Z",
      "browser_download_url": "https://github.com/andreasgriffin/bitcoin-safe/releases/download/1.0.0b2/Bitcoin-Safe-1.0.0b2.msi"
    },
    {
      "url": "https://api.github.com/repos/andreasgriffin/bitcoin-safe/releases/assets/203615974",
      "id": 203615974,
      "node_id": "RA_kwDOJfpJyM4MIu7m",
      "name": "Bitcoin-Safe-1.0.0b2.msi.asc",
      "label": "",
      "uploader": {
        "login": "andreasgriffin",
        "id": 116060138,
        "node_id": "U_kgDOBurv6g",
        "avatar_url": "https://avatars.githubusercontent.com/u/116060138?v=4",
        "gravatar_id": "",
        "url": "https://api.github.com/users/andreasgriffin",
        "html_url": "https://github.com/andreasgriffin",
        "followers_url": "https://api.github.com/users/andreasgriffin/followers",
        "following_url": "https://api.github.com/users/andreasgriffin/following{/other_user}",
        "gists_url": "https://api.github.com/users/andreasgriffin/gists{/gist_id}",
        "starred_url": "https://api.github.com/users/andreasgriffin/starred{/owner}{/repo}",
        "subscriptions_url": "https://api.github.com/users/andreasgriffin/subscriptions",
        "organizations_url": "https://api.github.com/users/andreasgriffin/orgs",
        "repos_url": "https://api.github.com/users/andreasgriffin/repos",
        "events_url": "https://api.github.com/users/andreasgriffin/events{/privacy}",
        "received_events_url": "https://api.github.com/users/andreasgriffin/received_events",
        "type": "User",
        "user_view_type": "public",
        "site_admin": false
      },
      "content_type": "application/octet-stream",
      "state": "uploaded",
      "size": 833,
      "download_count": 1,
      "created_at": "2024-11-02T15:50:23Z",
      "updated_at": "2024-11-02T15:50:23Z",
      "browser_download_url": "https://github.com/andreasgriffin/bitcoin-safe/releases/download/1.0.0b2/Bitcoin-Safe-1.0.0b2.msi.asc"
    },
    {
      "url": "https://api.github.com/repos/andreasgriffin/bitcoin-safe/releases/assets/203615976",
      "id": 203615976,
      "node_id": "RA_kwDOJfpJyM4MIu7o",
      "name": "bitcoin_safe-1.0.0b2-x86_64.AppImage",
      "label": "",
      "uploader": {
        "login": "andreasgriffin",
        "id": 116060138,
        "node_id": "U_kgDOBurv6g",
        "avatar_url": "https://avatars.githubusercontent.com/u/116060138?v=4",
        "gravatar_id": "",
        "url": "https://api.github.com/users/andreasgriffin",
        "html_url": "https://github.com/andreasgriffin",
        "followers_url": "https://api.github.com/users/andreasgriffin/followers",
        "following_url": "https://api.github.com/users/andreasgriffin/following{/other_user}",
        "gists_url": "https://api.github.com/users/andreasgriffin/gists{/gist_id}",
        "starred_url": "https://api.github.com/users/andreasgriffin/starred{/owner}{/repo}",
        "subscriptions_url": "https://api.github.com/users/andreasgriffin/subscriptions",
        "organizations_url": "https://api.github.com/users/andreasgriffin/orgs",
        "repos_url": "https://api.github.com/users/andreasgriffin/repos",
        "events_url": "https://api.github.com/users/andreasgriffin/events{/privacy}",
        "received_events_url": "https://api.github.com/users/andreasgriffin/received_events",
        "type": "User",
        "user_view_type": "public",
        "site_admin": false
      },
      "content_type": "application/octet-stream",
      "state": "uploaded",
      "size": 231756992,
      "download_count": 2,
      "created_at": "2024-11-02T15:50:24Z",
      "updated_at": "2024-11-02T15:51:54Z",
      "browser_download_url": "https://github.com/andreasgriffin/bitcoin-safe/releases/download/1.0.0b2/bitcoin_safe-1.0.0b2-x86_64.AppImage"
    },
    {
      "url": "https://api.github.com/repos/andreasgriffin/bitcoin-safe/releases/assets/203615970",
      "id": 203615970,
      "node_id": "RA_kwDOJfpJyM4MIu7i",
      "name": "bitcoin_safe-1.0.0b2-x86_64.AppImage.asc",
      "label": "",
      "uploader": {
        "login": "andreasgriffin",
        "id": 116060138,
        "node_id": "U_kgDOBurv6g",
        "avatar_url": "https://avatars.githubusercontent.com/u/116060138?v=4",
        "gravatar_id": "",
        "url": "https://api.github.com/users/andreasgriffin",
        "html_url": "https://github.com/andreasgriffin",
        "followers_url": "https://api.github.com/users/andreasgriffin/followers",
        "following_url": "https://api.github.com/users/andreasgriffin/following{/other_user}",
        "gists_url": "https://api.github.com/users/andreasgriffin/gists{/gist_id}",
        "starred_url": "https://api.github.com/users/andreasgriffin/starred{/owner}{/repo}",
        "subscriptions_url": "https://api.github.com/users/andreasgriffin/subscriptions",
        "organizations_url": "https://api.github.com/users/andreasgriffin/orgs",
        "repos_url": "https://api.github.com/users/andreasgriffin/repos",
        "events_url": "https://api.github.com/users/andreasgriffin/events{/privacy}",
        "received_events_url": "https://api.github.com/users/andreasgriffin/received_events",
        "type": "User",
        "user_view_type": "public",
        "site_admin": false
      },
      "content_type": "application/octet-stream",
      "state": "uploaded",
      "size": 833,
      "download_count": 1,
      "created_at": "2024-11-02T15:50:23Z",
      "updated_at": "2024-11-02T15:50:23Z",
      "browser_download_url": "https://github.com/andreasgriffin/bitcoin-safe/releases/download/1.0.0b2/bitcoin_safe-1.0.0b2-x86_64.AppImage.asc"
    }
  ],
  "tarball_url": "https://api.github.com/repos/andreasgriffin/bitcoin-safe/tarball/1.0.0b2",
  "zipball_url": "https://api.github.com/repos/andreasgriffin/bitcoin-safe/zipball/1.0.0b2",
  "body": "### New Features\r\n\r\n- Added German Language\r\n- Added GIF export for animated QR codes\r\n- Sync tab, which allows chat, synchronization and backup of labels, is now called **SyncTalk** \r\n\r\n### Improvements\r\n\r\n- When a tab is closed, the last activated tab is selected\r\n- Various UI bug fixes\r\n\r\n####  Verify signature\r\n\r\nImport my [public key](https://keys.openpgp.org/vks/v1/by-fingerprint/2759AA7148568ECCB03B76301D82124B440F612D) and verify the signature with:\r\n```\r\ngpg import 2759AA7148568ECCB03B76301D82124B440F612D.asc\r\ngpg --verify Bitcoin-Safe-1.0.0b2-x86_64.AppImage.asc\r\n```\r\n\r\n#### Install and run on Mac, Linux, or Windows \r\n```\r\npython3 -m pip install bitcoin-safe\r\npython3 -m bitcoin_safe\r\n```\r\n"
}
